Workbook

Sheet Cover
B3: [DOCUMENT TITLE]
B4: Level of Effort
A5: JUNIPER - Network - Mist Ai Network
B6: Generated: | C6: November 16, 2025
B7: Solution: | C7: [Solution Name]
B8: Customer: | C8: [Customer Name]
B9: Version: | C9: 1.0
B10: Status: | C10: Draft
C12: eoframework.org

Sheet Scope Assumptions
A1: SCOPE ASSUMPTIONS - BASELINE (MULTIPLIER 1.0)
A2: Category | B2: Baseline Assumption | C2: Current Scope | D2: Small (1x) | E2: Medium (2x) | F2: Large (3x) | G2: Notes
A3: Solution Scope | B3: WiFi 6E Access Points | C3: 50 Juniper AP45 APs | D3: 50 APs single building | E3: 150 APs multi-building | F3: 500+ APs campus | G3: Enterprise wireless deployment with Mist AI
A4: Solution Scope | B4: Wired Assurance | C4: 4 EX4400 PoE switches | D4: 4 EX4400 switches | E4: 12 EX4400 switches | F4: 30+ EX switches | G4: Wired infrastructure with AI-driven management
A5: Integration | B5: SSIDs and VLANs | C5: 3-5 wireless networks | D5: 3-5 SSIDs (corp guest IoT) | E5: 8-10 SSIDs multi-tenant | F5: 15+ SSIDs complex segmentation | G5: Wireless network segmentation and access control
A6: Integration | B6: External System Integrations | C6: 2 integrations | D6: 2 integrations (auth monitoring) | E6: 4-6 systems | F6: 8+ systems or complex protocols | G6: RADIUS SIEM and authentication integration
A7: Integration | B7: Location Services | C7: Indoor positioning enabled | D7: vBLE for 1 building | E7: vBLE for multi-building campus | F7: Advanced wayfinding asset tracking | G7: Virtual Bluetooth LE and location analytics
A8: User Base | B8: Concurrent Wireless Users | C8: 500-1000 concurrent users | D8: 500-1000 users | E8: 2000-5000 users | F8: 10000+ users | G8: Peak concurrent wireless client capacity
A9: User Base | B9: Network Administrators | C9: 3 wireless administrators | D9: 2-3 administrators | E9: 5-8 administrators | F9: 12+ administrators | G9: Wireless network administrators and operators
A10: Data Volume | B10: Access Point Count | C10: 50 access points | D10: 50 APs single site | E10: 150 APs multi-site | F10: 500+ APs campus | G10: Total AP deployment for coverage and capacity
A11: Data Volume | B11: Client Device Count | C11: 2000 total devices | D11: 2000 devices | E11: 8000 devices | F11: 20000+ devices | G11: Total wireless client device inventory
A12: Technical Environment | B12: Building Types | C12: Office commercial building | D12: Single building type | E12: Multi-building campus | F12: Complex campus multiple building types | G12: Facility type and RF environment complexity
A13: Technical Environment | B13: Deployment Locations | C13: Single building multi-floor | D13: Single building | E13: 2-3 buildings | F13: 5+ buildings or campus | G13: Geographic distribution for wireless deployment
... A19: Environment | B19: Deployment Environments | C19: 2 environments (staging prod) | D19: 2 environments | E19: 3 environments (dev stage prod) | F19: 4+ environments with lab | G19: Environment management for wireless deployment

Sheet Estimate Settings
A1: ESTIMATE SETTINGS
A2: Phase | B2: Variable Name | C2: Multiplier | D2: Description / Applies To Tasks
A3: Discovery | B3: DISCOVERY_MX | C3: 1 | D3: All Discovery phase tasks (Wireless Requirements Assessment, Facility Assessment, Network Integration Analysis)
A4: Planning | B4: PLANNING_MX | C4: 1 | D4: All Planning phase tasks (RF Site Survey, WLAN Architecture Design, Location Services Design, Implementation Planning)
A5: Development | B5: DEVELOPMENT_MX | C5: 1 | D5: All Development phase tasks (Switch Infrastructure Deployment, Mist Cloud Configuration, AP Installation, Authentication Integration, Marvis AI Activation, Location Services Setup, Wired Assurance Config)
A6: Testing | B6: TESTING_MX | C6: 1 | D6: All Testing phase tasks (RF Validation Testing, Client Connectivity Testing, Location Services Testing, Performance Testing, User Acceptance Testing)
A7: Deployment | B7: DEPLOYMENT_MX | C7: 1 | D7: All Deployment phase tasks (Legacy AP Decommissioning, Go-Live Support)
A8: Training | B8: TRAINING_MX | C8: 1 | D8: All Training phase tasks (Mist Dashboard Training, Marvis AI Training, Documentation Development)
A9: Closeout | B9: CLOSEOUT_MX | C9: 1 | D9: All Closeout phase tasks (Knowledge Transfer, SLE Baseline Establishment)
A10: Management | B10: MANAGEMENT_MX | C10: 1.5 | D10: Project Management overhead - 10% of actual engineering hours
A11: Leadership | B11: LEADERSHIP_MX | C11: 1.5 | D11: Quarterback/Technical Leadership overhead - 10% of actual engineering hours
A13: EO Sales Engineer Updates Multipliers Based on Customer Scope

Sheet LOE
A1: Level of Effort
A2: Phase | B2: Work Package | C2: Task Description | D2: Resource Type | E2: Base Hours | F2: Effort Multiplier | G2: Actual Hours | H2: Rate | I2: Cost Estimate | J2: Dependencies | K2: Notes
A3: Discovery | B3: Wireless Requirements Assessment | C3: Analyze current wireless infrastructure coverage and performance issues | D3: EO Engineer | E3: 32 | F3: ='Estimate Settings'!$C$3 | G3: =$E3*$F3 | H3: 200 | I3: =TEXT($G3*$H3,"$#,##0") | K3: Document WiFi dead zones user complaints and capacity needs
A4: Discovery | B4: Facility Assessment | C4: Review building layouts construction materials and coverage requirements | D4: EO Engineer | E4: 24 | F4: ='Estimate Settings'!$C$3 | G4: =$E4*$F4 | H4: 200 | I4: =TEXT($G4*$H4,"$#,##0") | K4: Building floor plans and RF propagation analysis for AP placement
A5: Discovery | B5: Network Integration Analysis | C5: Assess existing wired network VLANs and authentication infrastructure | D5: EO Engineer | E5: 16 | F5: ='Estimate Settings'!$C$3 | G5: =$E5*$F5 | H5: 175 | I5: =TEXT($G5*$H5,"$#,##0") | K5: VLAN design DHCP scopes and RADIUS integration requirements
A6: Planning | B6: RF Site Survey | C6: Conduct predictive RF site survey using Mist AI planning tools | D6: EO Engineer | E6: 40 | F6: ='Estimate Settings'!$C$4 | G6: =$E6*$F6 | H6: 200 | I6: =TEXT($G6*$H6,"$#,##0") | J6: Facility Assessment | K6: Deliverable: AP placement design for optimal coverage and capacity
A7: Planning | B7: WLAN Architecture Design | C7: Design SSID strategy VLAN segmentation and security policies | D7: EO Engineer | E7: 32 | F7: ='Estimate Settings'!$C$4 | G7: =$E7*$F7 | H7: 200 | I7: =TEXT($G7*$H7,"$#,##0") | J7: Network Integration Analysis | K7: Corporate guest IoT and voice wireless networks architecture
A8: Planning | B8: Location Services Design | C8: Design vBLE indoor positioning wayfinding and asset tracking | D8: EO Engineer | E8: 24 | F8: ='Estimate Settings'!$C$4 | G8: =$E8*$F8 | H8: 200 | I8: =TEXT($G8*$H8,"$#,##0") | J8: RF Site Survey | K8: Location-based services and occupancy analytics requirements
A9: Planning | B9: Implementation Planning | C9: Develop AP installation schedule and cutover strategy | D9: EO Engineer | E9: 16 | F9: ='Estimate Settings'!$C$4 | G9: =$E9*$F9 | H9: 150 | I9: =TEXT($G9*$H9,"$#,##0") | J9: WLAN Architecture Design | K9: Deliverable: Minimize business disruption during wireless deployment
A10: Development | B10: Switch Infrastructure Deployment | C10: Deploy and configure EX4400 PoE switches for AP power and connectivity | D10: EO Engineer | E10: 32 | F10: ='Estimate Settings'!$C$5 | G10: =$E10*$F10 | H10: 200 | I10: =TEXT($G10*$H10,"$#,##0") | J10: Implementation Planning | K10: 4 switches with uplinks to existing network and PoE capacity
A11: Development | B11: Mist Cloud Configuration | C11: Configure Mist cloud with SSIDs VLANs RF policies and security settings | D11: EO Engineer | E11: 40 | F11: ='Estimate Settings'!$C$5 | G11: =$E11*$F11 | H11: 200 | I11: =TEXT($G11*$H11,"$#,##0") | J11: Switch Infrastructure Deployment | K11: WLAN profiles RF templates and wireless policy deployment
A12: Development | B12: AP Installation | C12: Mount cable and deploy 50 Juniper AP45 WiFi 6E access points | D12: EO Engineer | E12: 100 | F12: ='Estimate Settings'!$C$5 | G12: =$E12*$F12 | H12: 150 | I12: =TEXT($G12*$H12,"$#,##0") | J12: Mist Cloud Configuration | K12: Physical installation across multiple buildings and floors
A13: Development | B13: Authentication Integration | C13: Integrate Mist with RADIUS Active Directory or SSO for enterprise auth | D13: EO Engineer | E13: 24 | F13: ='Estimate Settings'!$C$5 | G13: =$E13*$F13 | H13: 200 | I13: =TEXT($G13*$H13,"$#,##0") | J13: AP Installation | K13: 802.1X configuration and user authentication testing validation
A14: Development | B14: Marvis AI Activation | C14: Enable Marvis VNA for AI-driven troubleshooting and anomaly detection | D14: EO Engineer | E14: 16 | F14: ='Estimate Settings'!$C$5 | G14: =$E14*$F14 | H14: 200 | I14: =TEXT($G14*$H14,"$#,##0") | J14: Authentication Integration | K14: AI virtual assistant configuration and SLE baseline establishment
A15: Development | B15: Location Services Setup | C15: Configure vBLE indoor positioning wayfinding maps and asset tracking | D15: EO Engineer | E15: 32 | F15: ='Estimate Settings'!$C$5 | G15: =$E15*$F15 | H15: 200 | I15: =TEXT($G15*$H15,"$#,##0") | J15: Marvis AI Activation | K15: Virtual BLE beacons location analytics and wayfinding setup
A16: Development | B16: Wired Assurance Config | C16: Onboard EX4400 switches to Wired Assurance for unified management | D16: EO Engineer | E16: 16 | F16: ='Estimate Settings'!$C$5 | G16: =$E16*$F16 | H16: 180 | I16: =TEXT($G16*$H16,"$#,##0") | J16: Location Services Setup | K16: Wired network visibility and AI-driven switch operations
A17: Testing | B17: RF Validation Testing | C17: Conduct coverage testing throughput validation and roaming verification | D17: EO Engineer | E17: 40 | F17: ='Estimate Settings'!$C$6 | G17: =$E17*$F17 | H17: 200 | I17: =TEXT($G17*$H17,"$#,##0") | J17: Wired Assurance Config | K17: Walk-through testing with spectrum analyzer and wireless client devices
A18: Testing | B18: Client Connectivity Testing | C18: Test authentication client onboarding and application performance | D18: EO Engineer | E18: 24 | F18: ='Estimate Settings'!$C$6 | G18: =$E18*$F18 | H18: 175 | I18: =TEXT($G18*$H18,"$#,##0") | J18: RF Validation Testing | K18: Validate corporate guest IoT and voice wireless network connectivity
A19: Testing | B19: Location Services Testing | C19: Validate vBLE accuracy wayfinding navigation and asset tracking | D19: EO Engineer | E19: 16 | F19: ='Estimate Settings'!$C$6 | G19: =$E19*$F19 | H19: 175 | I19: =TEXT($G19*$H19,"$#,##0") | J19: Client Connectivity Testing | K19: Indoor positioning accuracy and mobile app integration testing
A20: Testing | B20: Performance Testing | C20: Conduct throughput testing with high-density client load | D20: EO Engineer | E20: 16 | F20: ='Estimate Settings'!$C$6 | G20: =$E20*$F20 | H20: 200 | I20: =TEXT($G20*$H20,"$#,##0") | J20: Location Services Testing | K20: Validate capacity and performance under real-world wireless conditions
A21: Testing | B21: User Acceptance Testing | C21: Coordinate UAT with IT and business users for production readiness | D21: EO Engineer | E21: 24 | F21: ='Estimate Settings'!$C$6 | G21: =$E21*$F21 | H21: 150 | I21: =TEXT($G21*$H21,"$#,##0") | J21: Performance Testing | K21: End-user validation of wireless coverage performance and features
A22: Deployment | B22: Legacy AP Decommissioning | C22: Decommission old wireless infrastructure and migrate to Mist APs | D22: EO Engineer | E22: 32 | F22: ='Estimate Settings'!$C$7 | G22: =$E22*$F22 | H22: 175 | I22: =TEXT($G22*$H22,"$#,##0") | J22: User Acceptance Testing | K22: Incremental AP cutover with minimal business disruption
A23: Deployment | B23: Go-Live Support | C23: Provide on-site support during production cutover and initial operation | D23: EO Engineer | E23: 40 | F23: ='Estimate Settings'!$C$7 | G23: =$E23*$F23 | H23: 200 | I23: =TEXT($G23*$H23,"$#,##0") | J23: Legacy AP Decommissioning | K23: First week post-deployment support and wireless issue resolution
A24: Training | B24: Mist Dashboard Training | C24: Train IT administrators on Mist cloud dashboard and configuration | D24: EO Engineer | E24: 16 | F24: ='Estimate Settings'!$C$8 | G24: =$E24*$F24 | H24: 200 | I24: =TEXT($G24*$H24,"$#,##0") | J24: Go-Live Support | K24: 2-day hands-on training for wireless network administrators
A25: Training | B25: Marvis AI Training | C25: Train IT staff on Marvis VNA conversational AI and troubleshooting | D25: EO Engineer | E25: 8 | F25: ='Estimate Settings'!$C$8 | G25: =$E25*$F25 | H25: 200 | I25: =TEXT($G25*$H25,"$#,##0") | J25: Mist Dashboard Training | K25: AI-driven operations and proactive wireless monitoring training
A26: Training | B26: Documentation Development | C26: Create as-built RF maps configuration guides and troubleshooting runbooks | D26: EO Engineer | E26: 32 | F26: ='Estimate Settings'!$C$8 | G26: =$E26*$F26 | H26: 150 | I26: =TEXT($G26*$H26,"$#,##0") | J26: Marvis AI Training | K26: Deliverable: Operational documentation and wireless knowledge transfer
A27: Closeout | B27: Knowledge Transfer | C27: Transfer solution ownership to IT operations and support teams | D27: EO Engineer | E27: 16 | F27: ='Estimate Settings'!$C$9 | G27: =$E27*$F27 | H27: 175 | I27: =TEXT($G27*$H27,"$#,##0") | J27: Documentation Development | K27: Comprehensive handover including operational procedures and escalation
A28: Closeout | B28: SLE Baseline Establishment | C28: Establish Service Level Expectation baselines for client experience monitoring | D28: EO Engineer | E28: 8 | F28: ='Estimate Settings'!$C$9 | G28: =$E28*$F28 | H28: 150 | I28: =TEXT($G28*$H28,"$#,##0") | J28: Knowledge Transfer | K28: Successful connects time to connect throughput roaming capacity SLEs
A29: Management | B29: Technical Leadership | C29: Wireless architecture oversight and RF design review | D29: EO Quarterback | E29: =ROUND(SUM($G$3:$G$28)*0.10,0) | F29: ='Estimate Settings'!$C$11 | G29: =$E29*$F29 | H29: 200 | I29: =TEXT($G29*$H29,"$#,##0") | K29: 25% of engineering effort for wireless technical guidance and escalation
A30: Management | B30: Project Management | C30: Project coordination stakeholder management and timeline oversight | D30: EO Project Manager | E30: =ROUND(SUM($G$3:$G$28)*0.10,0) | F30: ='Estimate Settings'!$C$10 | G30: =$E30*$F30 | H30: 150 | I30: =TEXT($G30*$H30,"$#,##0") | K30: 20% of engineering effort for wireless project delivery coordination
F31: TOTAL HOURS | G31: =SUM($G$3:$G$30) | H31: TOTAL COST | I31: =TEXT(SUMPRODUCT($G$3:$G$30,$H$3:$H$30),"$#,##0") | K31: EO Sales Engineer: Update phase-based multipliers in Estimate Settings based on wireless deployment scope

Sheet Credits
A1: Credits - Applied to Total Cost (Year 1 Only)
A2: Credit Type | B2: Credit Amount | C2: Credit Comments
A3: Juniper Partner Services Credit | B3: -8000 | C3: Juniper Partner Network credit for wireless architecture and Mist AI deployment services
A4: Implementation Discount | B4: 0 | C4: No implementation discount applicable
A5: TOTAL | B5: =SUMPRODUCT($G$3:$G$30,$H$3:$H$30)-8000
