Workbook

Sheet Cover
B3: [DOCUMENT TITLE]
B4: Infrastructure Costs
B5: Presales Document
B6: Generated: | C6: November 16, 2025
B7: Solution: | C7: November 22, 2025
B8: Customer: | C8: Advanced Security
B9: Version: | C9: [Customer Name]
B10: Status: | C10: Draft
C12: eoframework.org

Sheet Sizing Guidelines
A1: Sizing Guidelines
A2: Category | B2: Component | C2: Small | D2: Medium | E2: Large | F2: Notes
A3: Developer Licenses | B3: Active Developers | C3: 25 developers | D3: 100 developers | E3: 500 developers | F3: GitHub Enterprise + GHAS pricing
A4: Developer Licenses | B4: Active Committers | C4: 20 committers | D4: 80 committers | E4: 400 committers | F4: GHAS pricing based on 90-day commit activity
A5: Repository Scope | B5: Total Repositories | C5: 50 repositories | D5: 200 repositories | E5: 1000 repositories | F5: Code scanning coverage
A6: Security Scanning | B6: Code Scanning Frequency | C6: Per pull request | D6: Per commit | E6: Continuous | F6: CodeQL analysis frequency
A7: Security Scanning | B7: Languages Supported | C7: 2-3 languages | D7: 5-7 languages | E7: 10+ languages | F7: JavaScript Python Java C# Go Ruby etc
A8: Security Features | B8: CodeQL Queries | C8: Standard queries | D8: + Custom queries | E8: + Advanced patterns | F8: Security policy enforcement
A9: Security Features | B9: Secret Scanning | C9: Partner patterns | D9: + Custom patterns | E9: + Push protection | F9: API keys tokens credentials
A10: Security Features | B10: Dependency Scanning | C10: Basic SCA | D10: + Policy enforcement | E10: + Auto-remediation | F10: Dependabot alerts and updates
A11: CI/CD Integration | B11: GitHub Actions Minutes | C11: 10K minutes/month | D11: 50K minutes/month | E11: 200K+ minutes/month | F11: Included in Enterprise Cloud
A12: Professional Services | B12: Implementation Hours | C12: 40 hours | D12: 120 hours | E12: 300 hours | F12: Assessment integration training

Sheet Infrastructure Costs
A1: Infrastructure Costs
A2: Category | B2: Component | C2: Description | D2: Quantity | E2: Unit | F2: Unit Price | G2: Annual Cost | H2: Year 2 | I2: Year 3 | J2: 3-Year Total | K2: Notes
A3: Software Licenses | B3: GitHub Enterprise Cloud | C3: Enterprise Cloud with Advanced Security (100 users) | D3: 100 | E3: Users/Year | F3: 4200 | G3: =D3*F3 | H3: =G3 | I3: =G3 | J3: =G3+H3+I3 | K3: Includes GHAS code scanning secret scanning
A4: Software Licenses | B4: GitHub Actions Minutes | C4: Included compute minutes for CI/CD workflows | D4: 50000 | E4: Minutes/Month | F4: 0 | G4: =D4*F4*12 | H4: =G4 | I4: =G4 | J4: =G4+H4+I4 | K4: Included with Enterprise Cloud
A5: Software Licenses | B5: GitHub Packages Storage | C5: Package registry storage for artifacts (100 GB) | D5: 100 | E5: GB/Month | F5: 0.25 | G5: =D5*F5*12 | H5: =G5 | I5: =G5 | J5: =G5+H5+I5 | K5: Docker npm Maven NuGet packages
A6: Software Licenses | B6: GitHub LFS Storage | C6: Large file storage for binaries (50 GB) | D6: 50 | E6: GB/Month | F6: 0.07 | G6: =D6*F6*12 | H6: =G6 | I6: =G6 | J6: =G6+H6+I6 | K6: Binary assets and large files
A7: Professional Services | B7: Security Assessment | C7: Current state security posture assessment | D7: 40 | E7: Hours | F7: 225 | G7: =D7*F7 | H7: =0 | I7: =0 | J7: =G7+H7+I7 | K7: Vulnerability landscape analysis
A8: Professional Services | B8: GHAS Implementation | C8: GitHub Advanced Security setup and configuration | D8: 60 | E8: Hours | F8: 225 | G8: =D8*F8 | H8: =0 | I8: =0 | J8: =G8+H8+I8 | K8: Code scanning secret scanning setup
A9: Professional Services | B9: CodeQL Custom Queries | C9: Custom CodeQL query development for org-specific patterns | D9: 60 | E9: Hours | F9: 225 | G9: =D9*F9 | H9: =0 | I9: =0 | J9: =G9+H9+I9 | K9: Company security policies
A10: Professional Services | B10: Policy Configuration | C10: Security policies branch protection PR checks | D10: 30 | E10: Hours | F10: 200 | G10: =D10*F10 | H10: =0 | I10: =0 | J10: =G10+H10+I10 | K10: Merge blocking and approval rules
A11: Professional Services | B11: CI/CD Integration | C11: GitHub Actions workflow integration with scanning | D11: 40 | E11: Hours | F11: 200 | G11: =D11*F11 | H11: =0 | I11: =0 | J11: =G11+H11+I11 | K11: Automated security in pipelines
A12: Professional Services | B12: SIEM Integration | C12: Integration with Splunk Azure Sentinel | D12: 24 | E12: Hours | F12: 225 | G12: =D12*F12 | H12: =0 | I12: =0 | J12: =G12+H12+I12 | K12: Security event forwarding
A13: Professional Services | B13: Security Champion Training | C13: Train security champions on GHAS (8 champions) | D13: 16 | E13: Hours | F13: 175 | G13: =D13*F13 | H13: =0 | I13: =0 | J13: =G13+H13+I13 | K13: 2 days training for champions
A14: Professional Services | B14: Developer Training | C14: Developer workshops on fixing vulnerabilities | D14: 24 | E14: Hours | F14: 175 | G14: =D14*F14 | H14: =0 | I14: =0 | J14: =G14+H14+I14 | K14: 3 days training for dev teams
A15: Professional Services | B15: Administrator Training | C15: Platform admin training for GHAS management | D15: 8 | E15: Hours | F15: 175 | G15: =D15*F15 | H15: =0 | I15: =0 | J15: =G15+H15+I15 | K15: 1 day training for admins
A16: Third-Party Tools | B16: Vulnerability Database | C16: CVE database and threat intelligence feeds | D16: 1 | E16: Subscription/Year | F16: 5000 | G16: =D16*F16 | H16: =G16 | I16: =G16 | J16: =G16+H16+I16 | K16: Enhanced vulnerability data
A17: Third-Party Tools | B17: Code Quality Analysis | C17: SonarQube Developer Edition (100 users) | D17: 100 | E17: Users/Year | F17: 150 | G17: =D17*F17 | H17: =G17 | I17: =G17 | J17: =G17+H17+I17 | K17: Complementary code quality
A18: Support & Maintenance | B18: GitHub Premium Support | C18: 24x7 premium support with 1-hour response SLA | D18: 1 | E18: Service/Year | F18: 25000 | G18: =D18*F18 | H18: =G18 | I18: =G18 | J18: =G18+H18+I18 | K18: Enterprise-grade support
A19: Support & Maintenance | B19: Managed Services | C19: Ongoing GHAS management and optimization (10% of licenses) | D19: 1 | E19: Service/Year | F19: 42000 | G19: =D19*F19 | H19: =G19 | I19: =G19 | J19: =G19+H19+I19 | K19: Quarterly security reviews
A20: TOTAL | G20: =SUM(G3:G19) | H20: =SUM(H3:H19) | I20: =SUM(I3:I19) | J20: =SUM(J3:J19)

Sheet Credits
A1: Credits
A2: Category | B2: Credit Type | C2: Credit Amount | D2: Credit Comments
A3: Software Licenses | B3: GitHub Enterprise Credit | C3: 0 | D3: No discounts applied - list pricing
A4: Professional Services | B4: Implementation Credit | C4: 0 | D4: No professional services credits
A5: Third-Party Tools | B5: Partner Credit | C5: 0 | D5: No third-party tool credits
A6: Support & Maintenance | B6: Support Credit | C6: 0 | D6: No support credits available

Sheet 3-Year Summary
A1: 3-Year Summary
A2: Category | B2: Year 1 List | C2: Year 1 Credits | D2: Year 1 Net | E2: Year 2 | F2: Year 3 | G2: 3-Year Total
A3: Software Licenses | B3: =SUMIF('Infrastructure Costs'!$A:$A,A3,'Infrastructure Costs'!$G:$G) | C3: =SUMIF(Credits!$A:$A,A3,Credits!$C:$C) | D3: =B3+C3 | E3: =SUMIF('Infrastructure Costs'!$A:$A,A3,'Infrastructure Costs'!$H:$H) | F3: =SUMIF('Infrastructure Costs'!$A:$A,A3,'Infrastructure Costs'!$I:$I) | G3: =D3+E3+F3
A4: Professional Services | B4: =SUMIF('Infrastructure Costs'!$A:$A,A4,'Infrastructure Costs'!$G:$G) | C4: =SUMIF(Credits!$A:$A,A4,Credits!$C:$C) | D4: =B4+C4 | E4: =SUMIF('Infrastructure Costs'!$A:$A,A4,'Infrastructure Costs'!$H:$H) | F4: =SUMIF('Infrastructure Costs'!$A:$A,A4,'Infrastructure Costs'!$I:$I) | G4: =D4+E4+F4
A5: Third-Party Tools | B5: =SUMIF('Infrastructure Costs'!$A:$A,A5,'Infrastructure Costs'!$G:$G) | C5: =SUMIF(Credits!$A:$A,A5,Credits!$C:$C) | D5: =B5+C5 | E5: =SUMIF('Infrastructure Costs'!$A:$A,A5,'Infrastructure Costs'!$H:$H) | F5: =SUMIF('Infrastructure Costs'!$A:$A,A5,'Infrastructure Costs'!$I:$I) | G5: =D5+E5+F5
A6: Support & Maintenance | B6: =SUMIF('Infrastructure Costs'!$A:$A,A6,'Infrastructure Costs'!$G:$G) | C6: =SUMIF(Credits!$A:$A,A6,Credits!$C:$C) | D6: =B6+C6 | E6: =SUMIF('Infrastructure Costs'!$A:$A,A6,'Infrastructure Costs'!$H:$H) | F6: =SUMIF('Infrastructure Costs'!$A:$A,A6,'Infrastructure Costs'!$I:$I) | G6: =D6+E6+F6
A7: **TOTAL INVESTMENT** | B7: =SUM(B3:B6) | C7: =SUM(C3:C6) | D7: =SUM(D3:D6) | E7: =SUM(E3:E6) | F7: =SUM(F3:F6) | G7: =SUM(G3:G6)
