Workbook

Sheet Cover
B3: [DOCUMENT TITLE]
B4: Discovery Questionnaire
B5: Presales Document
B6: Generated: | C6: November 16, 2025
B7: Solution: | C7: November 22, 2025
B8: Customer: | C8: Sentinel Siem
B9: Version: | C9: [Customer Name]
B10: Status: | C10: Draft
C12: eoframework.org

Sheet All Categories (Read Only)
A1: Total Questions | B1: Answered | C1: Remaining | D1: % Complete
A2: 33 | B2: =SUMPRODUCT(--(LEN(F5:F37)>0)) | C2: =A2-B2 | D2: =B2/A2
A4: Category | B4: Question | C4: Response_Type | D4: Required | E4: Options | F4: Description | G4: Impact
A5: =IF('Business Context'!A2="","",'Business Context'!A2) | B5: =IF('Business Context'!B2="","",'Business Context'!B2) | C5: =IF('Business Context'!C2="","",'Business Context'!C2) | D5: =IF('Business Context'!D2="","",'Business Context'!D2) | E5: =IF('Business Context'!E2="","",'Business Context'!E2) | F5: =IF('Business Context'!F2="","",'Business Context'!F2) | G5: =IF('Business Context'!G2="","",'Business Context'!G2)
A6: =IF('Business Context'!A3="","",'Business Context'!A3) | B6: =IF('Business Context'!B3="","",'Business Context'!B3) | C6: =IF('Business Context'!C3="","",'Business Context'!C3) | D6: =IF('Business Context'!D3="","",'Business Context'!D3) | E6: =IF('Business Context'!E3="","",'Business Context'!E3) | F6: =IF('Business Context'!F3="","",'Business Context'!F3) | G6: =IF('Business Context'!G3="","",'Business Context'!G3)
A7: =IF('Business Context'!A4="","",'Business Context'!A4) | B7: =IF('Business Context'!B4="","",'Business Context'!B4) | C7: =IF('Business Context'!C4="","",'Business Context'!C4) | D7: =IF('Business Context'!D4="","",'Business Context'!D4) | E7: =IF('Business Context'!E4="","",'Business Context'!E4) | F7: =IF('Business Context'!F4="","",'Business Context'!F4) | G7: =IF('Business Context'!G4="","",'Business Context'!G4)
A8: =IF('Business Context'!A5="","",'Business Context'!A5) | B8: =IF('Business Context'!B5="","",'Business Context'!B5) | C8: =IF('Business Context'!C5="","",'Business Context'!C5) | D8: =IF('Business Context'!D5="","",'Business Context'!D5) | E8: =IF('Business Context'!E5="","",'Business Context'!E5) | F8: =IF('Business Context'!F5="","",'Business Context'!F5) | G8: =IF('Business Context'!G5="","",'Business Context'!G5)
A9: =IF('Business Context'!A6="","",'Business Context'!A6) | B9: =IF('Business Context'!B6="","",'Business Context'!B6) | C9: =IF('Business Context'!C6="","",'Business Context'!C6) | D9: =IF('Business Context'!D6="","",'Business Context'!D6) | E9: =IF('Business Context'!E6="","",'Business Context'!E6) | F9: =IF('Business Context'!F6="","",'Business Context'!F6) | G9: =IF('Business Context'!G6="","",'Business Context'!G6)
A10: =IF('Business Context'!A7="","",'Business Context'!A7) | B10: =IF('Business Context'!B7="","",'Business Context'!B7) | C10: =IF('Business Context'!C7="","",'Business Context'!C7) | D10: =IF('Business Context'!D7="","",'Business Context'!D7) | E10: =IF('Business Context'!E7="","",'Business Context'!E7) | F10: =IF('Business Context'!F7="","",'Business Context'!F7) | G10: =IF('Business Context'!G7="","",'Business Context'!G7)
A11: =IF('Technology Infrastructure'!A2="","",'Technology Infrastructure'!A2) | B11: =IF('Technology Infrastructure'!B2="","",'Technology Infrastructure'!B2) | C11: =IF('Technology Infrastructure'!C2="","",'Technology Infrastructure'!C2) | D11: =IF('Technology Infrastructure'!D2="","",'Technology Infrastructure'!D2) | E11: =IF('Technology Infrastructure'!E2="","",'Technology Infrastructure'!E2) | F11: =IF('Technology Infrastructure'!F2="","",'Technology Infrastructure'!F2) | G11: =IF('Technology Infrastructure'!G2="","",'Technology Infrastructure'!G2)
A12: =IF('Technology Infrastructure'!A3="","",'Technology Infrastructure'!A3) | B12: =IF('Technology Infrastructure'!B3="","",'Technology Infrastructure'!B3) | C12: =IF('Technology Infrastructure'!C3="","",'Technology Infrastructure'!C3) | D12: =IF('Technology Infrastructure'!D3="","",'Technology Infrastructure'!D3) | E12: =IF('Technology Infrastructure'!E3="","",'Technology Infrastructure'!E3) | F12: =IF('Technology Infrastructure'!F3="","",'Technology Infrastructure'!F3) | G12: =IF('Technology Infrastructure'!G3="","",'Technology Infrastructure'!G3)
A13: =IF('Technology Infrastructure'!A4="","",'Technology Infrastructure'!A4) | B13: =IF('Technology Infrastructure'!B4="","",'Technology Infrastructure'!B4) | C13: =IF('Technology Infrastructure'!C4="","",'Technology Infrastructure'!C4) | D13: =IF('Technology Infrastructure'!D4="","",'Technology Infrastructure'!D4) | E13: =IF('Technology Infrastructure'!E4="","",'Technology Infrastructure'!E4) | F13: =IF('Technology Infrastructure'!F4="","",'Technology Infrastructure'!F4) | G13: =IF('Technology Infrastructure'!G4="","",'Technology Infrastructure'!G4)
A14: =IF('Technology Infrastructure'!A5="","",'Technology Infrastructure'!A5) | B14: =IF('Technology Infrastructure'!B5="","",'Technology Infrastructure'!B5) | C14: =IF('Technology Infrastructure'!C5="","",'Technology Infrastructure'!C5) | D14: =IF('Technology Infrastructure'!D5="","",'Technology Infrastructure'!D5) | E14: =IF('Technology Infrastructure'!E5="","",'Technology Infrastructure'!E5) | F14: =IF('Technology Infrastructure'!F5="","",'Technology Infrastructure'!F5) | G14: =IF('Technology Infrastructure'!G5="","",'Technology Infrastructure'!G5)
A15: =IF('Technology Infrastructure'!A6="","",'Technology Infrastructure'!A6) | B15: =IF('Technology Infrastructure'!B6="","",'Technology Infrastructure'!B6) | C15: =IF('Technology Infrastructure'!C6="","",'Technology Infrastructure'!C6) | D15: =IF('Technology Infrastructure'!D6="","",'Technology Infrastructure'!D6) | E15: =IF('Technology Infrastructure'!E6="","",'Technology Infrastructure'!E6) | F15: =IF('Technology Infrastructure'!F6="","",'Technology Infrastructure'!F6) | G15: =IF('Technology Infrastructure'!G6="","",'Technology Infrastructure'!G6)
A16: =IF('Technical Requirements'!A2="","",'Technical Requirements'!A2) | B16: =IF('Technical Requirements'!B2="","",'Technical Requirements'!B2) | C16: =IF('Technical Requirements'!C2="","",'Technical Requirements'!C2) | D16: =IF('Technical Requirements'!D2="","",'Technical Requirements'!D2) | E16: =IF('Technical Requirements'!E2="","",'Technical Requirements'!E2) | F16: =IF('Technical Requirements'!F2="","",'Technical Requirements'!F2) | G16: =IF('Technical Requirements'!G2="","",'Technical Requirements'!G2)
A17: =IF('Technical Requirements'!A3="","",'Technical Requirements'!A3) | B17: =IF('Technical Requirements'!B3="","",'Technical Requirements'!B3) | C17: =IF('Technical Requirements'!C3="","",'Technical Requirements'!C3) | D17: =IF('Technical Requirements'!D3="","",'Technical Requirements'!D3) | E17: =IF('Technical Requirements'!E3="","",'Technical Requirements'!E3) | F17: =IF('Technical Requirements'!F3="","",'Technical Requirements'!F3) | G17: =IF('Technical Requirements'!G3="","",'Technical Requirements'!G3)
A18: =IF('Technical Requirements'!A4="","",'Technical Requirements'!A4) | B18: =IF('Technical Requirements'!B4="","",'Technical Requirements'!B4) | C18: =IF('Technical Requirements'!C4="","",'Technical Requirements'!C4) | D18: =IF('Technical Requirements'!D4="","",'Technical Requirements'!D4) | E18: =IF('Technical Requirements'!E4="","",'Technical Requirements'!E4) | F18: =IF('Technical Requirements'!F4="","",'Technical Requirements'!F4) | G18: =IF('Technical Requirements'!G4="","",'Technical Requirements'!G4)
A19: =IF('Technical Requirements'!A5="","",'Technical Requirements'!A5) | B19: =IF('Technical Requirements'!B5="","",'Technical Requirements'!B5) | C19: =IF('Technical Requirements'!C5="","",'Technical Requirements'!C5) | D19: =IF('Technical Requirements'!D5="","",'Technical Requirements'!D5) | E19: =IF('Technical Requirements'!E5="","",'Technical Requirements'!E5) | F19: =IF('Technical Requirements'!F5="","",'Technical Requirements'!F5) | G19: =IF('Technical Requirements'!G5="","",'Technical Requirements'!G5)
A20: =IF('Technical Requirements'!A6="","",'Technical Requirements'!A6) | B20: =IF('Technical Requirements'!B6="","",'Technical Requirements'!B6) | C20: =IF('Technical Requirements'!C6="","",'Technical Requirements'!C6) | D20: =IF('Technical Requirements'!D6="","",'Technical Requirements'!D6) | E20: =IF('Technical Requirements'!E6="","",'Technical Requirements'!E6) | F20: =IF('Technical Requirements'!F6="","",'Technical Requirements'!F6) | G20: =IF('Technical Requirements'!G6="","",'Technical Requirements'!G6)
A21: =IF('Technical Requirements'!A7="","",'Technical Requirements'!A7) | B21: =IF('Technical Requirements'!B7="","",'Technical Requirements'!B7) | C21: =IF('Technical Requirements'!C7="","",'Technical Requirements'!C7) | D21: =IF('Technical Requirements'!D7="","",'Technical Requirements'!D7) | E21: =IF('Technical Requirements'!E7="","",'Technical Requirements'!E7) | F21: =IF('Technical Requirements'!F7="","",'Technical Requirements'!F7) | G21: =IF('Technical Requirements'!G7="","",'Technical Requirements'!G7)
A22: =IF('Technical Requirements'!A8="","",'Technical Requirements'!A8) | B22: =IF('Technical Requirements'!B8="","",'Technical Requirements'!B8) | C22: =IF('Technical Requirements'!C8="","",'Technical Requirements'!C8) | D22: =IF('Technical Requirements'!D8="","",'Technical Requirements'!D8) | E22: =IF('Technical Requirements'!E8="","",'Technical Requirements'!E8) | F22: =IF('Technical Requirements'!F8="","",'Technical Requirements'!F8) | G22: =IF('Technical Requirements'!G8="","",'Technical Requirements'!G8)
A23: =IF('Organizational'!A2="","",'Organizational'!A2) | B23: =IF('Organizational'!B2="","",'Organizational'!B2) | C23: =IF('Organizational'!C2="","",'Organizational'!C2) | D23: =IF('Organizational'!D2="","",'Organizational'!D2) | E23: =IF('Organizational'!E2="","",'Organizational'!E2) | F23: =IF('Organizational'!F2="","",'Organizational'!F2) | G23: =IF('Organizational'!G2="","",'Organizational'!G2)
A24: =IF('Organizational'!A3="","",'Organizational'!A3) | B24: =IF('Organizational'!B3="","",'Organizational'!B3) | C24: =IF('Organizational'!C3="","",'Organizational'!C3) | D24: =IF('Organizational'!D3="","",'Organizational'!D3) | E24: =IF('Organizational'!E3="","",'Organizational'!E3) | F24: =IF('Organizational'!F3="","",'Organizational'!F3) | G24: =IF('Organizational'!G3="","",'Organizational'!G3)
A25: =IF('Organizational'!A4="","",'Organizational'!A4) | B25: =IF('Organizational'!B4="","",'Organizational'!B4) | C25: =IF('Organizational'!C4="","",'Organizational'!C4) | D25: =IF('Organizational'!D4="","",'Organizational'!D4) | E25: =IF('Organizational'!E4="","",'Organizational'!E4) | F25: =IF('Organizational'!F4="","",'Organizational'!F4) | G25: =IF('Organizational'!G4="","",'Organizational'!G4)
A26: =IF('Organizational'!A5="","",'Organizational'!A5) | B26: =IF('Organizational'!B5="","",'Organizational'!B5) | C26: =IF('Organizational'!C5="","",'Organizational'!C5) | D26: =IF('Organizational'!D5="","",'Organizational'!D5) | E26: =IF('Organizational'!E5="","",'Organizational'!E5) | F26: =IF('Organizational'!F5="","",'Organizational'!F5) | G26: =IF('Organizational'!G5="","",'Organizational'!G5)
A27: =IF('Organizational'!A6="","",'Organizational'!A6) | B27: =IF('Organizational'!B6="","",'Organizational'!B6) | C27: =IF('Organizational'!C6="","",'Organizational'!C6) | D27: =IF('Organizational'!D6="","",'Organizational'!D6) | E27: =IF('Organizational'!E6="","",'Organizational'!E6) | F27: =IF('Organizational'!F6="","",'Organizational'!F6) | G27: =IF('Organizational'!G6="","",'Organizational'!G6)
A28: =IF('Organizational'!A7="","",'Organizational'!A7) | B28: =IF('Organizational'!B7="","",'Organizational'!B7) | C28: =IF('Organizational'!C7="","",'Organizational'!C7) | D28: =IF('Organizational'!D7="","",'Organizational'!D7) | E28: =IF('Organizational'!E7="","",'Organizational'!E7) | F28: =IF('Organizational'!F7="","",'Organizational'!F7) | G28: =IF('Organizational'!G7="","",'Organizational'!G7)
A29: =IF('Budget'!A2="","",'Budget'!A2) | B29: =IF('Budget'!B2="","",'Budget'!B2) | C29: =IF('Budget'!C2="","",'Budget'!C2) | D29: =IF('Budget'!D2="","",'Budget'!D2) | E29: =IF('Budget'!E2="","",'Budget'!E2) | F29: =IF('Budget'!F2="","",'Budget'!F2) | G29: =IF('Budget'!G2="","",'Budget'!G2)
A30: =IF('Budget'!A3="","",'Budget'!A3) | B30: =IF('Budget'!B3="","",'Budget'!B3) | C30: =IF('Budget'!C3="","",'Budget'!C3) | D30: =IF('Budget'!D3="","",'Budget'!D3) | E30: =IF('Budget'!E3="","",'Budget'!E3) | F30: =IF('Budget'!F3="","",'Budget'!F3) | G30: =IF('Budget'!G3="","",'Budget'!G3)
A31: =IF('Budget'!A4="","",'Budget'!A4) | B31: =IF('Budget'!B4="","",'Budget'!B4) | C31: =IF('Budget'!C4="","",'Budget'!C4) | D31: =IF('Budget'!D4="","",'Budget'!D4) | E31: =IF('Budget'!E4="","",'Budget'!E4) | F31: =IF('Budget'!F4="","",'Budget'!F4) | G31: =IF('Budget'!G4="","",'Budget'!G4)
A32: =IF('Budget'!A5="","",'Budget'!A5) | B32: =IF('Budget'!B5="","",'Budget'!B5) | C32: =IF('Budget'!C5="","",'Budget'!C5) | D32: =IF('Budget'!D5="","",'Budget'!D5) | E32: =IF('Budget'!E5="","",'Budget'!E5) | F32: =IF('Budget'!F5="","",'Budget'!F5) | G32: =IF('Budget'!G5="","",'Budget'!G5)
A33: =IF('Success Criteria'!A2="","",'Success Criteria'!A2) | B33: =IF('Success Criteria'!B2="","",'Success Criteria'!B2) | C33: =IF('Success Criteria'!C2="","",'Success Criteria'!C2) | D33: =IF('Success Criteria'!D2="","",'Success Criteria'!D2) | E33: =IF('Success Criteria'!E2="","",'Success Criteria'!E2) | F33: =IF('Success Criteria'!F2="","",'Success Criteria'!F2) | G33: =IF('Success Criteria'!G2="","",'Success Criteria'!G2)
A34: =IF('Success Criteria'!A3="","",'Success Criteria'!A3) | B34: =IF('Success Criteria'!B3="","",'Success Criteria'!B3) | C34: =IF('Success Criteria'!C3="","",'Success Criteria'!C3) | D34: =IF('Success Criteria'!D3="","",'Success Criteria'!D3) | E34: =IF('Success Criteria'!E3="","",'Success Criteria'!E3) | F34: =IF('Success Criteria'!F3="","",'Success Criteria'!F3) | G34: =IF('Success Criteria'!G3="","",'Success Criteria'!G3)
A35: =IF('Success Criteria'!A4="","",'Success Criteria'!A4) | B35: =IF('Success Criteria'!B4="","",'Success Criteria'!B4) | C35: =IF('Success Criteria'!C4="","",'Success Criteria'!C4) | D35: =IF('Success Criteria'!D4="","",'Success Criteria'!D4) | E35: =IF('Success Criteria'!E4="","",'Success Criteria'!E4) | F35: =IF('Success Criteria'!F4="","",'Success Criteria'!F4) | G35: =IF('Success Criteria'!G4="","",'Success Criteria'!G4)
A36: =IF('Success Criteria'!A5="","",'Success Criteria'!A5) | B36: =IF('Success Criteria'!B5="","",'Success Criteria'!B5) | C36: =IF('Success Criteria'!C5="","",'Success Criteria'!C5) | D36: =IF('Success Criteria'!D5="","",'Success Criteria'!D5) | E36: =IF('Success Criteria'!E5="","",'Success Criteria'!E5) | F36: =IF('Success Criteria'!F5="","",'Success Criteria'!F5) | G36: =IF('Success Criteria'!G5="","",'Success Criteria'!G5)
A37: =IF('Success Criteria'!A6="","",'Success Criteria'!A6) | B37: =IF('Success Criteria'!B6="","",'Success Criteria'!B6) | C37: =IF('Success Criteria'!C6="","",'Success Criteria'!C6) | D37: =IF('Success Criteria'!D6="","",'Success Criteria'!D6) | E37: =IF('Success Criteria'!E6="","",'Success Criteria'!E6) | F37: =IF('Success Criteria'!F6="","",'Success Criteria'!F6) | G37: =IF('Success Criteria'!G6="","",'Success Criteria'!G6)

Sheet Business Context
A1: Category | B1: Question | C1: Response_Type | D1: Required | E1: Options | F1: Description | G1: Impact
A2: Business Context | B2: What is your current annual security incident volume? | C2: Number | D2: Yes | F2: Number of security incidents detected and investigated annually | G2: High
A3: Business Context | B3: What are your primary security threats and concerns? | C3: Multiple Choice | D3: Yes | E3: Ransomware,Insider threats,Data exfiltration,Compliance violations,APT attacks,Lateral movement,Zero-day exploits,Other | F3: Current security threat landscape and priorities | G3: High
A4: Business Context | B4: What are your security and compliance mandates? | C4: Multiple Choice | D4: Yes | E4: HIPAA,PCI-DSS,GDPR,SOC 2,ISO 27001,NIST Cybersecurity Framework,Industry-specific regulations,Other | F4: Regulatory and compliance requirements | G4: High
A5: Business Context | B5: What is your current annual security operations budget? | C5: Number | D5: Yes | F5: Total spend on security tools personnel and infrastructure | G5: High
A6: Business Context | B6: What are your primary business drivers for SIEM investment? | C6: Multiple Choice | D6: Yes | E6: Reduce incident response time,Improve threat detection,Meet compliance requirements,Achieve cost optimization,Enable advanced threat hunting,Consolidate security tools,Improve visibility,Other | F6: Key motivations for implementing SIEM solution | G6: High
A7: Business Context | B7: What are your specific security goals and KPIs? | C7: Text | D7: Yes | F7: Quantified targets for MTTR mean time to respond detection accuracy | G7: High

Sheet Technology Infrastructure
A1: Category | B1: Question | C1: Response_Type | D1: Required | E1: Options | F1: Description | G1: Impact
A2: Technology Infrastructure | B2: What security tools are you currently using? | C2: Multiple Choice | D2: No | E2: Endpoint Detection Response,Intrusion Detection,Firewall,Proxy,Data Loss Prevention,Web Application Firewall,Others | F2: Current security tool stack for integration planning | G2: Medium
A3: Technology Infrastructure | B3: What are your current data sources for security monitoring? | C3: Multiple Choice | D3: Yes | E3: Firewalls,Intrusion Detection Systems,Endpoint Detection Response,Cloud Platforms,Identity Management,Databases,Applications,Network Devices,Email Systems,Other | F3: Sources to integrate with SIEM | G3: High
A4: Technology Infrastructure | B4: How do you currently monitor Azure cloud environments? | C4: Multiple Choice | D4: Yes | E4: Manual log collection,Third-party SIEM,Cloud-native monitoring,Azure Monitor only,No visibility,Other | F4: Azure security monitoring capabilities | G4: High
A5: Technology Infrastructure | B5: How do you currently manage security incidents? | C5: Multiple Choice | D5: Yes | E5: Manual process,Ticketing system,SOAR platform,Workflow automation,Paper-based,Combination of tools,Other | F5: Incident management methodology | G5: Medium
A6: Technology Infrastructure | B6: What is your team's technical expertise level? | C6: Scale | D6: Yes | E6: High,Medium,Low | F6: Experience levels for training and support planning | G6: Medium

Sheet Technical Requirements
A1: Category | B1: Question | C1: Response_Type | D1: Required | E1: Options | F1: Description | G1: Impact
A2: Technical Requirements | B2: What are your security analytics requirements? | C2: Multiple Choice | D2: Yes | E2: Real-time alerting,Anomaly detection,Behavioral analytics,Threat intelligence integration,Custom rules,Forensic analysis,Compliance reporting,Other | F2: Analytics capabilities needed | G2: High
A3: Technical Requirements | B3: What are your SOAR automation requirements? | C3: Multiple Choice | D3: Yes | E3: Incident response automation,Threat intelligence enrichment,False positive reduction,Integration with external systems,Custom playbooks,Other | F3: SOAR and automation needs | G3: Medium
A4: Technical Requirements | B4: What is your preferred deployment approach? | C4: Multiple Choice | D4: Yes | E4: Public cloud,Hybrid cloud,On-premises,No preference | F4: Infrastructure and deployment preferences | G4: High
A5: Technical Requirements | B5: What are your data residency and compliance requirements? | C5: Text | D5: Yes | F5: Geographic regulatory and data sovereignty requirements | G5: High
A6: Technical Requirements | B6: What are your security and access control requirements? | C6: Multiple Choice | D6: Yes | E6: Single sign-on,Multi-factor authentication,Role-based access control,Data encryption,Network isolation,Audit logging,Privileged access management,Other | F6: Security and compliance needs | G6: High
A7: Technical Requirements | B7: What are your performance and scalability requirements? | C7: Text | D7: Yes | F7: Data volumes ingestion rates and growth projections | G7: High
A8: Technical Requirements | B8: What third-party integrations are required? | C8: Text | D8: Yes | F8: Specific security tools platforms and systems needing integration | G8: High

Sheet Organizational
A1: Category | B1: Question | C1: Response_Type | D1: Required | E1: Options | F1: Description | G1: Impact
A2: Organizational | B2: Who will be involved in the solution implementation? | C2: Text | D2: Yes | F2: Security team IT infrastructure compliance stakeholders | G2: Medium
A3: Organizational | B3: What is your team's current security expertise? | C3: Scale | D3: Yes | E3: High,Medium,Low | F3: Skill levels in SIEM and security operations | G3: Medium
A4: Organizational | B4: What training and support will be needed? | C4: Text | D4: Yes | F4: SOC analyst security engineer operational support needs | G4: Medium
A5: Organizational | B5: What is your preferred implementation timeline? | C5: Text | D5: Yes | F5: Project start phases and go-live timelines | G5: High
A6: Organizational | B6: How do you want to approach implementation? | C6: Multiple Choice | D6: Yes | E6: Big bang deployment,Phased by data source,Phased by use case,Parallel with existing SIEM,Pilot program,Other | F6: Implementation strategy and risk management | G6: Medium
A7: Organizational | B7: How will you measure solution success? | C7: Text | D7: Yes | F7: Key performance indicators and success metrics | G7: High

Sheet Budget
A1: Category | B1: Question | C1: Response_Type | D1: Required | E1: Options | F1: Description | G1: Impact
A2: Budget | B2: What is your total project budget range? | C2: Range | D2: Yes | E2: $200K-$500K,$500K-$1M,$1M-$2.5M,$2.5M+ | F2: Available investment for solution implementation | G2: High
A3: Budget | B3: What is your annual operational budget? | C3: Range | D3: Yes | E3: $100K-$300K,$300K-$600K,$600K-$1M,$1M+ | F3: Ongoing operational and licensing budget | G3: Medium
A4: Budget | B4: How do you evaluate technology investments? | C4: Multiple Choice | D4: Yes | E4: Total Cost of Ownership,Return on Investment,Risk Reduction Value,Operational Efficiency,Business case development,Other | F4: Investment evaluation criteria | G4: Medium
A5: Budget | B5: What are your cost optimization priorities? | C5: Multiple Choice | D5: Yes | E5: Minimize upfront costs,Optimize ongoing costs,Flexible scaling,Predictable costs,Maximum security value for budget | F5: Cost management preferences | G5: Medium

Sheet Success Criteria
A1: Category | B1: Question | C1: Response_Type | D1: Required | E1: Options | F1: Description | G1: Impact
A2: Success Criteria | B2: What are your target improvements for MTTR? | C2: Text | D2: Yes | F2: Expected mean time to respond reduction target | G2: High
A3: Success Criteria | B3: What are your target improvements for threat detection rate? | C3: Text | D3: Yes | F3: Expected improvement in threats detected automatically | G3: High
A4: Success Criteria | B4: What are your compliance reporting requirements? | C4: Text | D4: Yes | F4: Specific compliance reports and audit trail needs | G4: High
A5: Success Criteria | B5: What are your primary concerns about implementation? | C5: Multiple Choice | D5: Yes | E5: Complexity of implementation,User adoption by SOC team,Data integration challenges,Performance under load,Vendor lock-in,Skill gaps,Budget overruns,Other | F5: Implementation risks and concerns | G5: Medium
A6: Success Criteria | B6: What risk mitigation strategies are important? | C6: Multiple Choice | D6: Yes | E6: Comprehensive pilot testing,Phased implementation,Extensive training,Strong vendor support,Performance guarantees,SLA commitments | F6: Risk management preferences | G6: Medium
